ksalib/__init__.py
ksalib/ksa.py
ksalib/parserlib.py
ksalib/simplefunctions.py
ksalib-0.1.0.dist-info/LICENSE
ksalib-0.1.0.dist-info/METADATA
ksalib-0.1.0.dist-info/WHEEL
ksalib-0.1.0.dist-info/top_level.txt
ksalib-0.1.0.dist-info/RECORD
