Metadata-Version: 2.1
Name: ksalib
Version: 0.1.0
Summary: A library for KSA
Home-page: https://github.com/andyyeyeye/ksalib
Author: andyyeyeye
Author-email: andyye.jongcye@gmail.com
License: The MIT License
Platform: UNKNOWN
Requires-Dist: requests
Requires-Dist: bs4
Requires-Dist: html2text
